README.md
setup.py
pyauto/__init__.py
pyauto/config.py
pyauto/deploy.py
pyauto/j2util.py
pyauto/strutil.py
pyauto/tasks.py
pyauto/template.py
pyauto/uriutil.py
pyauto/yamlutil.py
pyauto.egg-info/PKG-INFO
pyauto.egg-info/SOURCES.txt
pyauto.egg-info/dependency_links.txt
pyauto.egg-info/requires.txt
pyauto.egg-info/top_level.txt
test/test_config.py
test/test_strutil.py
test/test_tasks.py
test/test_template.py
test/test_uriutil.py
test/test_yamlutil.py