Metadata-Version: 1.0
Name: pyauto
Version: 0.0.2
Summary: PyAuto Core
Home-page: https://github.com/adamjaso/pyauto
Author: Adam Jaso
Author-email: UNKNOWN
License: UNKNOWN
Platform: UNKNOWN
